suitesparseget/__init__.py
suitesparseget/suitesparseget.py
suitesparsegetpy-0.1.1.dist-info/licenses/LICENSE
suitesparsegetpy-0.1.1.dist-info/METADATA
suitesparsegetpy-0.1.1.dist-info/WHEEL
suitesparsegetpy-0.1.1.dist-info/top_level.txt
suitesparsegetpy-0.1.1.dist-info/RECORD
