Metadata-Version: 2.4
Name: suitesparsegetpy
Version: 0.1.1
Summary: Get SuiteSparse matrices into Python
Author-email: Bernie Roesler <bernard.roesler@gmail.com>
License: MIT
Project-URL: Github, https://github.com/broesler/suitesparseget_py
Requires-Python: >=3.10
License-File: LICENSE
Requires-Dist: numpy>=2.1
Requires-Dist: pandas>=2.3
Requires-Dist: pymatreader>=1.1
Requires-Dist: Requests>=2.32
Requires-Dist: scipy>=1.15
Requires-Dist: toml
Provides-Extra: dev
Requires-Dist: pytest; extra == "dev"
Requires-Dist: ruff; extra == "dev"
Dynamic: license-file
